nymstr/__init__.py
nymstr/_modidx.py
nymstr/core.py
nymstr-0.0.12.dist-info/LICENSE
nymstr-0.0.12.dist-info/METADATA
nymstr-0.0.12.dist-info/WHEEL
nymstr-0.0.12.dist-info/entry_points.txt
nymstr-0.0.12.dist-info/top_level.txt
nymstr-0.0.12.dist-info/RECORD
