Metadata-Version: 2.1
Name: nymstr
Version: 0.0.12
Summary: nymstr
Home-page: https://github.com/dsm-72/nymstr
Author: dsm-72
Author-email: sumner.magruder@yale.edu
License: Apache Software License 2.0
Keywords: name things with fuzzy string matching nymstr nym str fuz fuzstr atyp ispec indoc dynattr
Classifier: Development Status :: 4 - Beta
Classifier: Intended Audience :: Developers
Classifier: Natural Language :: English
Classifier: Programming Language :: Python :: 3.11
Classifier: License :: OSI Approved :: Apache Software License
Requires-Python: >=3.11
License-File: LICENSE
Requires-Dist: atyp
Requires-Dist: regsyn
Requires-Dist: indoc
Requires-Dist: ispec
Requires-Dist: pstr
Requires-Dist: fuzstr
Requires-Dist: aspec
Provides-Extra: dev
